welldium_wms_middleware_api_v_1_client/__init__.py
welldium_wms_middleware_api_v_1_client/api/__init__.py
welldium_wms_middleware_api_v_1_client/api/odoo/__init__.py
welldium_wms_middleware_api_v_1_client/api/odoo/delete_odoo_sales_order_id.py
welldium_wms_middleware_api_v_1_client/api/odoo/post_odoo_products.py
welldium_wms_middleware_api_v_1_client/api/odoo/post_odoo_sales_order_cancel_id.py
welldium_wms_middleware_api_v_1_client/api/odoo/post_odoo_sales_order_confirm_id.py
welldium_wms_middleware_api_v_1_client/api/selveo_webhooks/__init__.py
welldium_wms_middleware_api_v_1_client/api/selveo_webhooks/post_selveo_webhooks_sale_shipments.py
welldium_wms_middleware_api_v_1_client/api/selveo_webhooks/post_selveo_webhooks_sales_orders.py
welldium_wms_middleware_api_v_1_client/client.py
welldium_wms_middleware_api_v_1_client/errors.py
welldium_wms_middleware_api_v_1_client/models/__init__.py
welldium_wms_middleware_api_v_1_client/models/odoo_sync_product_request.py
welldium_wms_middleware_api_v_1_client/models/request.py
welldium_wms_middleware_api_v_1_client/models/request_2.py
welldium_wms_middleware_api_v_1_client/models/selveo_sale_order_webhook_data_type_0.py
welldium_wms_middleware_api_v_1_client/models/selveo_sale_shipment_webhook_data_type_0.py
welldium_wms_middleware_api_v_1_client/models/selveo_webhook_event_data_of_selveo_sale_order_webhook_data.py
welldium_wms_middleware_api_v_1_client/models/selveo_webhook_event_data_of_selveo_sale_shipment_webhook_data.py
welldium_wms_middleware_api_v_1_client/py.typed
welldium_wms_middleware_api_v_1_client/types.py
welldium_wms_middleware_api_v_1_client-2025.2.5.46.dist-info/METADATA
welldium_wms_middleware_api_v_1_client-2025.2.5.46.dist-info/WHEEL
welldium_wms_middleware_api_v_1_client-2025.2.5.46.dist-info/RECORD
